Metadata-Version: 1.1
Name: pyinfluxdb
Version: 0.1.3
Summary: A influxdb driver package.
Home-page: https://github.com/muumlover/pyinfluxdb
Author: MUUMLOVER
Author-email: muumlover@live.com
License: MPL
Download-URL: https://github.com/muumlover/pyinfluxdb/tarball/0.1.3
Platform: UNKNOWN
Classifier: Development Status :: 1 - Planning
Classifier: Intended Audience :: Developers
Classifier: Programming Language :: Python :: 3
